[
	{
		"name": "喵斯",
		"description": "請問你還有小魚乾嗎？一點點就好~",
		"skill": "在喵斯的應援下，主角的 Fever 狀態持續時間將延長 2 秒。",
		"chipName": "小魚乾",
		"chipDescription": "喵斯那傢伙是不是又偷吃小魚乾了？"
	},
	{
		"name": "安吉拉",
		"description": "守護天使降臨~",
		"skill": "每當主角受傷時，安吉拉將為主角減免 6 點傷害。",
		"chipName": "白色羽毛",
		"chipDescription": "安吉拉大人最近壓力好大呀。"
	},
	{
		"name": "塔納托斯",
		"description": "只要跑的夠快，死亡就追不上你。",
		"skill": "每當主角受傷或獲得紅心時，塔納托斯將使主角進入 2 秒的無敵時間。",
		"chipName": "玩具骨頭",
		"chipDescription": "塑料做成的骨頭，感覺一點也不可怕。"
	},
	{
		"name": "Rabot-233",
		"description": "我……這裡……有……用……不完……的……胡……蘿蔔……",
		"skill": "Rabot-233 可以將 5 個“Miss”判定轉化為“Great”判定；\n對樂譜（長按）和連打敵人無效。",
		"chipName": "合金胡蘿蔔",
		"chipDescription": "這根凝聚了高科技力量的胡蘿蔔真是太棒了ww"
	},
	{
		"name": "小護士",
		"description": "這種情況應該是治不好了吧？",
		"skill": "當主角的生命值不足 50 時，小護士將為主角每秒回复 10 點生命值，持續 15 秒；\n該治療效果僅生效一次。",
		"chipName": "小螺絲",
		"chipDescription": "機器壞了可以修，人壞了要怎麼辦呢？"
	},
	{
		"name": "小女巫",
		"description": "對不起%>_<%我的魔法還學得不夠深入。",
		"skill": "每當主角在 Fever 狀態下擊退敵人時，小女巫將幫助主角獲得 20% 的額外分數。",
		"chipName": "西瓜軟糖",
		"chipDescription": "用西瓜汁製作的西瓜軟糖，唔~~可以以假亂真了。"
	},
	{
		"name": "小龍女",
		"description": "我有一條小青龍~~小青龍~~~",
		"skill": "每當主角擊退來自 BOSS 的攻擊時，小龍女將幫助主角獲得 30% 的額外分數。",
		"chipName": "龍珠",
		"chipDescription": "傳說中集齊七顆就能召喚神龍了呢。"
	},
	{
		"name": "莉莉絲",
		"description": "我是來自地獄的莉莉絲大人呢~哦哈哈哈~~~~",
		"skill": "每當取得“Perfect”判定時，莉莉絲將幫助主角獲得 5% 的額外分數；\n若與小惡魔瑪莉嘉同行，則每個“Perfect”判定將為瑪莉嘉回复 2 點生命值。",
		"chipName": "蝙蝠翅膀",
		"chipDescription": "地獄的使者莉莉絲到處尋找的玩意。"
	},
	{
		"name": "佩奇醫生",
		"description": "",
		"skill": "來自節奏醫生的佩奇醫生化身精靈——每成功擊退累計7個敵人，將為主角回复2點生命值，且第7次擊中必定為“Perfect”； “Miss”判定變為“Great”；若 Note 為音符或紅心則自動接住。對樂譜（長按）、障礙（齒輪）和連打敵人無效。",
		"chipName": "聴診器",
		"chipDescription": "佩奇醫生的本體究竟是眼鏡，還是聽診器呢？"
	},
	{
		"name": "靜音靈",
		"description": "",
		"skill": "在靜音靈的干擾下，所選主角技能將會失效，生命值為預設值（250點）。",
		"chipName": "禁止牌棒棒糖",
		"chipDescription": "維護世界的和平只需要一根棒棒糖！"
	},
	{
		"name": "霓虹彩蛋",
		"description": "",
		"skill": "首次開啟 Fever 狀態後霓虹彩蛋將會隨機孵化出一位霓虹深淵聯動角色：R-6 可在主角每次受傷時減免一半傷害；紗夜可在取得“Perfect”判定時獲得 5% 的額外分數；琳可在持續按住樂譜（長按）期間，將“Miss”判定變為“Great”，對樂譜（長按）和連打敵人無效。",
		"chipName": "未孵化的蛋",
		"chipDescription": "你永遠無法到達“猜中彩蛋裡會有什麼”的真實( ﾟ∀。)"
	}
]